LICENSE
MANIFEST.in
README.md
requirements.txt
setup.cfg
setup.py
versioneer.py
mixpanel_export/__init__.py
mixpanel_export/_version.py
mixpanel_export/mixpanel_stream.py
mixpanel_export.egg-info/PKG-INFO
mixpanel_export.egg-info/SOURCES.txt
mixpanel_export.egg-info/dependency_links.txt
mixpanel_export.egg-info/requires.txt
mixpanel_export.egg-info/top_level.txt