Metadata-Version: 1.1
Name: mixpanel-export
Version: 0.2.post6
Summary: A streaming library for reading raw event data from Mixpanel's export API
Home-page: https://github.com/ownaginatious/mixpanel-export-stream
Author: Dillon Dixon
Author-email: dillondixon@gmail.com
License: MIT
Keywords: mixpanel,export,stream
Platform: UNKNOWN
Classifier: License :: OSI Approved :: MIT License
Classifier: Programming Language :: Python :: 2.7
Classifier: Programming Language :: Python :: 3.3
Classifier: Programming Language :: Python :: 3.4
Classifier: Programming Language :: Python :: 3.5
